{
  "IsRegenerate": true,
  "MenuPosition": "",
  "RelativeNamespace": "SalesInvoicePayments",
  "EntityName": "SalesInvoicePayment",
  "EntityNamePlural": "SalesInvoicePayments",
  "TableName": "SalesInvoicePayment",
  "PrimaryKeyType": "int",
  "BaseClass": "Entity",
  "EntityHistory": false,
  "AutoMigration": true,
  "UpdateDatabase": true,
  "CreateUserInterface": false,
  "CreateViewOnly": false,
  "CreateExcelExport": false,
  "IsNonModalCRUDPage": false,
  "IsMasterDetailPage": false,
  "PagePermission": {
    "Host": false,
    "Tenant": false
  },
  "Properties": [
    {
      "Name": "Date",
      "Type": "DateTime",
      "MaxLength": -1,
      "MinLength": -1,
      "Range": {
        "IsRangeSet": false,
        "MinimumValue": 0.0,
        "MaximumValue": 0.0
      },
      "Required": false,
      "Nullable": false,
      "Regex": "",
      "UserInterface": {
        "AdvancedFilter": false,
        "List": false,
        "CreateOrUpdate": false
      }
    },
    {
      "Name": "Amount",
      "Type": "decimal",
      "MaxLength": -1,
      "MinLength": -1,
      "Range": {
        "IsRangeSet": false,
        "MinimumValue": 0.0,
        "MaximumValue": 0.0
      },
      "Required": false,
      "Nullable": false,
      "Regex": "",
      "UserInterface": {
        "AdvancedFilter": false,
        "List": false,
        "CreateOrUpdate": false
      }
    }
  ],
  "NavigationProperties": [
    {
      "Namespace": "DDM.SalesInvoices",
      "ForeignEntityName": "SalesInvoice",
      "IdType": "int",
      "IsNullable": false,
      "PropertyName": "SalesInvoiceId",
      "DisplayPropertyName": "SalesInvoiceLineNames",
      "DuplicationNumber": 0,
      "RelationType": "single",
      "ViewType": "Dropdown"
    },
    {
      "Namespace": "DDM.PaymentMethods",
      "ForeignEntityName": "PaymentMethod",
      "IdType": "int",
      "IsNullable": false,
      "PropertyName": "PaymentMethodId",
      "DisplayPropertyName": "Name",
      "DuplicationNumber": 0,
      "RelationType": "single",
      "ViewType": "LookupTable"
    },
    {
      "Namespace": "DDM.SalesOrders",
      "ForeignEntityName": "SalesOrder",
      "IdType": "int",
      "IsNullable": false,
      "PropertyName": "SalesOrderId",
      "DisplayPropertyName": "SalesOrderLineNames",
      "DuplicationNumber": 0,
      "RelationType": "single",
      "ViewType": "LookupTable"
    }
  ],
  "NavigationPropertyOneToManyTables": [],
  "EnumDefinitions": [],
  "DbContext": null
}